{
  "bm25_search_docs": {
    "name": "bm25_search_docs",
    "description": "基于 BM25 的词法检索，适合查找专有名词、别名、缩写、物品名称、重复动作、引语和外观细节等需要精确词面命中的证据。",
    "parameters": [
      {
        "name": "query",
        "type": "string",
        "description": "关键词、名称、别名或想精确匹配的短语。",
        "required": true
      },
      {
        "name": "k",
        "type": "integer",
        "description": "返回条数，默认 10。",
        "required": false
      }
    ]
  },
  "lookup_document_ids_by_title": {
    "name": "lookup_document_ids_by_title",
    "description": "把场次或章节标题映射回对应的 document_id。",
    "parameters": [
      {
        "name": "title",
        "type": "string",
        "description": "场次或章节标题。",
        "required": false
      },
      {
        "name": "subtitle",
        "type": "string",
        "description": "可选副标题或子场景标题。",
        "required": false
      },
      {
        "name": "fuzzy",
        "type": "boolean",
        "description": "是否启用模糊匹配，默认 true。",
        "required": false
      },
      {
        "name": "limit",
        "type": "integer",
        "description": "最多返回多少个 document_id，默认 10。",
        "required": false
      }
    ]
  },
  "lookup_titles_by_document_ids": {
    "name": "lookup_titles_by_document_ids",
    "description": "把 document_id 映射成可读的场次或章节标题。",
    "parameters": [
      {
        "name": "document_ids",
        "type": "array",
        "description": "document_id 列表。",
        "required": true
      }
    ]
  },
  "search_related_content": {
    "name": "search_related_content",
    "description": "给定 document_id 和 query，读取对应原文并抽取与问题直接相关的内容。",
    "parameters": [
      {
        "name": "document_ids",
        "type": "array",
        "description": "待查看的 document_id 列表。",
        "required": true
      },
      {
        "name": "query",
        "type": "string",
        "description": "问题或抽取目标。",
        "required": true
      },
      {
        "name": "max_length",
        "type": "integer",
        "description": "每个文档返回的最大文本长度，默认 300。",
        "required": false
      }
    ]
  }
}
